{
    "name": "jacdac-v2-OOB",
    "version": "0.6.5",
    "description": "",
    "dependencies": {
        "core": "*",
        "radio": "*",
        "jacdac": "github:microsoft/pxt-jacdac",
        "jacdac-button": "github:microsoft/pxt-jacdac/button"
    },
    "files": [
        "main.ts",
        "services.ts",
        "README.md"
    ],
    "targetVersions": {
        "target": "3.1.79",
        "targetId": "microbit"
    },
    "supportedTargets": [
        "microbit"
    ],
    "preferredEditor": "tsprj"
}
